coral8/__init__.py
coral8/cli.py
coral8/core.py
coral8/deployer.py
coral8/exporter.py
coral8/injector.py
coral8/loader.py
coral8-0.6.0.dist-info/METADATA
coral8-0.6.0.dist-info/WHEEL
coral8-0.6.0.dist-info/entry_points.txt
coral8-0.6.0.dist-info/top_level.txt
coral8-0.6.0.dist-info/RECORD
