Metadata-Version: 2.4
Name: coral8
Version: 0.6.0
Summary: Zero-config file loader & simple HTTP bridge
Author-email: Dylan Kennedy <dylkenn89@gmail.com>
Requires-Python: >=3.8
Requires-Dist: typer>=0.7.0
Requires-Dist: openpyxl>=3.1
Provides-Extra: export
Requires-Dist: pandas>=2.0; extra == "export"
Requires-Dist: openpyxl>=3.1; extra == "export"
Provides-Extra: yaml
Requires-Dist: PyYAML>=6.0; extra == "yaml"
